postgres_permissions_operator/__init__.py
postgres_permissions_operator/postgres_permissions_operator.py
amsterdam_airflow_postgres_permissions_operator-1.2.dist-info/METADATA
amsterdam_airflow_postgres_permissions_operator-1.2.dist-info/WHEEL
amsterdam_airflow_postgres_permissions_operator-1.2.dist-info/RECORD
